databricks_pybuilder_plugin/__init__.py
databricks_pybuilder_plugin-0.1.6.dist-info/METADATA
databricks_pybuilder_plugin-0.1.6.dist-info/WHEEL
databricks_pybuilder_plugin-0.1.6.dist-info/namespace_packages.txt
databricks_pybuilder_plugin-0.1.6.dist-info/top_level.txt
databricks_pybuilder_plugin-0.1.6.dist-info/zip-safe
databricks_pybuilder_plugin-0.1.6.dist-info/RECORD
