Metadata-Version: 2.1
Name: databricks-pybuilder-plugin
Version: 0.1.6
Summary: Pybuilder plugin providing tasks for assets deployment.
Home-page: 
Author: Mikhail Kavaliou
Author-email: killswitch@tut.by
Maintainer: 
Maintainer-email: 
Classifier: Development Status :: 5 - Production/Stable
Requires-Dist: Jinja2
Requires-Dist: boto3
Requires-Dist: databricks-cli
